llm_launchpad/__init__.py
llm_launchpad/cli.py
llm_launchpad/presets.py
llm_launchpad-0.0.2.dist-info/licenses/LICENSE
llm_launchpad-0.0.2.dist-info/METADATA
llm_launchpad-0.0.2.dist-info/WHEEL
llm_launchpad-0.0.2.dist-info/entry_points.txt
llm_launchpad-0.0.2.dist-info/top_level.txt
llm_launchpad-0.0.2.dist-info/RECORD
