Metadata-Version: 2.4
Name: llm-launchpad
Version: 0.0.2
Summary: One-click personal LLM deployment with coding agent + chat UI.
Author: Thomas Rochefort-Bedard
License:                     GNU AFFERO GENERAL PUBLIC LICENSE
Project-URL: Homepage, https://github.com/ThomasRochefortB/llm-launchpad
Project-URL: Issues, https://github.com/ThomasRochefortB/llm-launchpad/issues
Keywords: llm,deployment,modal,agent,chat
Classifier: Programming Language :: Python :: 3
Classifier: License :: OSI Approved :: GNU Affero General Public License v3
Classifier: Operating System :: OS Independent
Requires-Python: >=3.9
License-File: LICENSE
Requires-Dist: modal>=0.60.0
Requires-Dist: typer>=0.12.3
Requires-Dist: rich>=13.7.1
Requires-Dist: InquirerPy>=0.3.4
Requires-Dist: requests>=2.32.0
Provides-Extra: hf
Requires-Dist: huggingface_hub[hf_transfer]>=0.26.2; extra == "hf"
Dynamic: license-file
